<annotation>
	<folder>1장:20cm</folder>
	<filename>a101.jpeg</filename>
	<path>/Users/jihoon/Desktop/data/1장:20cm/a101.jpeg</path>
	<source>
		<database>Unknown</database>
	</source>
	<size>
		<width>3024</width>
		<height>3024</height>
		<depth>3</depth>
	</size>
	<segmented>0</segmented>
	<object>
		<name>u</name>
		<pose>Unspecified</pose>
		<truncated>0</truncated>
		<difficult>0</difficult>
		<bndbox>
			<xmin>1639</xmin>
			<ymin>1510</ymin>
			<xmax>1739</xmax>
			<ymax>1655</ymax>
		</bndbox>
	</object>
</annotation>
