<annotation>
	<folder>2장:20cm:1칸</folder>
	<filename>b127.jpeg</filename>
	<path>/Users/yon_ninii/Desktop/data/2장:20cm:1칸/b127.jpeg</path>
	<source>
		<database>Unknown</database>
	</source>
	<size>
		<width>3024</width>
		<height>3024</height>
		<depth>3</depth>
	</size>
	<segmented>0</segmented>
	<object>
		<name>a</name>
		<pose>Unspecified</pose>
		<truncated>0</truncated>
		<difficult>0</difficult>
		<bndbox>
			<xmin>2615</xmin>
			<ymin>1582</ymin>
			<xmax>2711</xmax>
			<ymax>1723</ymax>
		</bndbox>
	</object>
	<object>
		<name>z</name>
		<pose>Unspecified</pose>
		<truncated>0</truncated>
		<difficult>0</difficult>
		<bndbox>
			<xmin>2456</xmin>
			<ymin>1582</ymin>
			<xmax>2560</xmax>
			<ymax>1741</ymax>
		</bndbox>
	</object>
</annotation>
