<annotation>
	<folder>2장:20cm:1칸</folder>
	<filename>b69.jpeg</filename>
	<path>/Users/yon_ninii/Desktop/data/2장:20cm:1칸/b69.jpeg</path>
	<source>
		<database>Unknown</database>
	</source>
	<size>
		<width>3024</width>
		<height>3024</height>
		<depth>3</depth>
	</size>
	<segmented>0</segmented>
	<object>
		<name>n</name>
		<pose>Unspecified</pose>
		<truncated>0</truncated>
		<difficult>0</difficult>
		<bndbox>
			<xmin>467</xmin>
			<ymin>1393</ymin>
			<xmax>563</xmax>
			<ymax>1537</ymax>
		</bndbox>
	</object>
	<object>
		<name>o</name>
		<pose>Unspecified</pose>
		<truncated>0</truncated>
		<difficult>0</difficult>
		<bndbox>
			<xmin>630</xmin>
			<ymin>1378</ymin>
			<xmax>745</xmax>
			<ymax>1519</ymax>
		</bndbox>
	</object>
</annotation>
